<?xml version="1.0" encoding="UTF-8"?>
<!DOCTYPE score-partwise PUBLIC "-//Recordare//DTD MusicXML 2.0 Partwise//EN" "http://www.musicxml.org/dtds/partwise.dtd">
<score-partwise>
  <identification>
    <encoding>
      <software>MuseScore 1.3</software>
      <encoding-date>2015-10-28</encoding-date>
      </encoding>
    </identification>
  <defaults>
    <scaling>
      <millimeters>7.05556</millimeters>
      <tenths>40</tenths>
      </scaling>
    <page-layout>
      <page-height>1683.78</page-height>
      <page-width>1190.55</page-width>
      <page-margins type="even">
        <left-margin>56.6929</left-margin>
        <right-margin>56.6929</right-margin>
        <top-margin>56.6929</top-margin>
        <bottom-margin>113.386</bottom-margin>
        </page-margins>
      <page-margins type="odd">
        <left-margin>56.6929</left-margin>
        <right-margin>56.6929</right-margin>
        <top-margin>56.6929</top-margin>
        <bottom-margin>113.386</bottom-margin>
        </page-margins>
      </page-layout>
    </defaults>
  <credit page="1">
    <credit-words default-x="595.275" default-y="1627.09" font-size="24" justify="center" valign="top">Solar</credit-words>
    </credit>
  <credit page="1">
    <credit-words default-x="1133.86" default-y="1560.09" font-size="12" justify="right" valign="top">Miles Davis</credit-words>
    </credit>
  <part-list>
    <score-part id="P1">
      <part-name></part-name>
      <score-instrument id="P1-I3">
        <instrument-name></instrument-name>
        </score-instrument>
      <midi-instrument id="P1-I3">
        <midi-channel>1</midi-channel>
        <midi-program>65</midi-program>
        <volume>78.7402</volume>
        <pan>0</pan>
        </midi-instrument>
      </score-part>
    </part-list>
  <part id="P1">
    <measure number="1" width="207.77">
      <print>
        <system-layout>
          <system-margins>
            <left-margin>-0.00</left-margin>
            <right-margin>0.00</right-margin>
            </system-margins>
          <top-system-distance>180.00</top-system-distance>
          </system-layout>
        </print>
      <attributes>
        <divisions>2</divisions>
        <key>
          <fifths>0</fifths>
          <mode>major</mode>
          </key>
        <time>
          <beats>4</beats>
          <beat-type>4</beat-type>
          </time>
        <clef>
          <sign>G</sign>
          <line>2</line>
          </clef>
        <transpose>
          <diatonic>-1</diatonic>
          <chromatic>-2</chromatic>
          </transpose>
        </attributes>
      <harmony print-frame="no">
        <root>
          <root-step>C</root-step>
          </root>
        <kind text="m">minor</kind>
        </harmony>
      <note>
        <rest/>
        <duration>1</duration>
        <voice>1</voice>
        <type>eighth</type>
        </note>
      <note default-x="94.17" default-y="-15.00">
        <pitch>
          <step>C</step>
          <octave>5</octave>
          </pitch>
        <duration>3</duration>
        <voice>1</voice>
        <type>quarter</type>
        <dot/>
        <stem>down</stem>
        </note>
      <note default-x="132.26" default-y="-20.00">
        <pitch>
          <step>B</step>
          <octave>4</octave>
          </pitch>
        <duration>2</duration>
        <voice>1</voice>
        <type>quarter</type>
        <stem>down</stem>
        </note>
      <note default-x="163.49" default-y="-10.00">
        <pitch>
          <step>D</step>
          <octave>5</octave>
          </pitch>
        <duration>1</duration>
        <voice>1</voice>
        <type>eighth</type>
        <stem>down</stem>
        <beam number="1">begin</beam>
        </note>
      <note default-x="183.01" default-y="-15.00">
        <pitch>
          <step>C</step>
          <octave>5</octave>
          </pitch>
        <duration>1</duration>
        <voice>1</voice>
        <type>eighth</type>
        <stem>down</stem>
        <beam number="1">end</beam>
        </note>
      </measure>
    <measure number="2" width="145.47">
      <harmony print-frame="no">
        <root>
          <root-step>C</root-step>
          </root>
        <kind text="m">minor</kind>
        </harmony>
      <note>
        <rest/>
        <duration>1</duration>
        <voice>1</voice>
        <type>eighth</type>
        </note>
      <note default-x="32.34" default-y="-30.00">
        <pitch>
          <step>G</step>
          <octave>4</octave>
          </pitch>
        <duration>3</duration>
        <tie type="start"/>
        <voice>1</voice>
        <type>quarter</type>
        <dot/>
        <stem>up</stem>
        <notations>
          <tied type="start"/>
          </notations>
        </note>
      <note default-x="72.02" default-y="-30.00">
        <pitch>
          <step>G</step>
          <octave>4</octave>
          </pitch>
        <duration>3</duration>
        <tie type="stop"/>
        <voice>1</voice>
        <type>quarter</type>
        <dot/>
        <stem>up</stem>
        <notations>
          <tied type="stop"/>
          </notations>
        </note>
      <note default-x="111.70" default-y="-25.00">
        <pitch>
          <step>A</step>
          <octave>4</octave>
          </pitch>
        <duration>1</duration>
        <voice>1</voice>
        <type>eighth</type>
        <stem>up</stem>
        </note>
      </measure>
    <measure number="3" width="159.95">
      <harmony print-frame="no">
        <root>
          <root-step>G</root-step>
          </root>
        <kind text="m7">minor-seventh</kind>
        </harmony>
      <note default-x="15.00" default-y="-20.00">
        <pitch>
          <step>B</step>
          <alter>-1</alter>
          <octave>4</octave>
          </pitch>
        <duration>2</duration>
        <voice>1</voice>
        <type>quarter</type>
        <accidental>flat</accidental>
        <stem>down</stem>
        </note>
      <note default-x="46.02" default-y="-20.00">
        <pitch>
          <step>B</step>
          <alter>-1</alter>
          <octave>4</octave>
          </pitch>
        <duration>1</duration>
        <voice>1</voice>
        <type>eighth</type>
        <stem>down</stem>
        <beam number="1">begin</beam>
        </note>
      <note default-x="65.40" default-y="-20.00">
        <pitch>
          <step>B</step>
          <alter>-1</alter>
          <octave>4</octave>
          </pitch>
        <duration>1</duration>
        <voice>1</voice>
        <type>eighth</type>
        <stem>down</stem>
        <beam number="1">end</beam>
        </note>
      <note default-x="84.79" default-y="-25.00">
        <pitch>
          <step>A</step>
          <octave>4</octave>
          </pitch>
        <duration>2</duration>
        <voice>1</voice>
        <type>quarter</type>
        <stem>up</stem>
        </note>
      <note default-x="115.80" default-y="-15.00">
        <pitch>
          <step>C</step>
          <octave>5</octave>
          </pitch>
        <duration>1</duration>
        <voice>1</voice>
        <type>eighth</type>
        <stem>down</stem>
        <beam number="1">begin</beam>
        </note>
      <note default-x="135.19" default-y="-20.00">
        <pitch>
          <step>B</step>
          <alter>-1</alter>
          <octave>4</octave>
          </pitch>
        <duration>1</duration>
        <tie type="start"/>
        <voice>1</voice>
        <type>eighth</type>
        <stem>down</stem>
        <beam number="1">end</beam>
        <notations>
          <tied type="start"/>
          </notations>
        </note>
      </measure>
    <measure number="4" width="77.78">
      <harmony print-frame="no">
        <root>
          <root-step>C</root-step>
          </root>
        <kind text="7">dominant</kind>
        </harmony>
      <note default-x="12.00" default-y="-20.00">
        <pitch>
          <step>B</step>
          <alter>-1</alter>
          <octave>4</octave>
          </pitch>
        <duration>8</duration>
        <tie type="stop"/>
        <voice>1</voice>
        <type>whole</type>
        <notations>
          <tied type="stop"/>
          </notations>
        </note>
      </measure>
    <measure number="5" width="169.72">
      <harmony print-frame="no">
        <root>
          <root-step>F</root-step>
          </root>
        <kind text="M7">major-seventh</kind>
        </harmony>
      <note>
        <rest/>
        <duration>1</duration>
        <voice>1</voice>
        <type>eighth</type>
        </note>
      <note default-x="35.83" default-y="-25.00">
        <pitch>
          <step>A</step>
          <octave>4</octave>
          </pitch>
        <duration>3</duration>
        <voice>1</voice>
        <type>quarter</type>
        <dot/>
        <stem>up</stem>
        </note>
      <note default-x="82.33" default-y="-30.00">
        <pitch>
          <step>G</step>
          <alter>1</alter>
          <octave>4</octave>
          </pitch>
        <duration>2</duration>
        <voice>1</voice>
        <type>quarter</type>
        <accidental>sharp</accidental>
        <stem>up</stem>
        </note>
      <note default-x="120.46" default-y="-20.00">
        <pitch>
          <step>B</step>
          <alter>-1</alter>
          <octave>4</octave>
          </pitch>
        <duration>1</duration>
        <voice>1</voice>
        <type>eighth</type>
        <accidental>flat</accidental>
        <stem>up</stem>
        <beam number="1">begin</beam>
        </note>
      <note default-x="144.29" default-y="-25.00">
        <pitch>
          <step>A</step>
          <octave>4</octave>
          </pitch>
        <duration>1</duration>
        <voice>1</voice>
        <type>eighth</type>
        <stem>up</stem>
        <beam number="1">end</beam>
        </note>
      </measure>
    <measure number="6" width="145.12">
      <harmony print-frame="no">
        <root>
          <root-step>F</root-step>
          </root>
        <kind text="M7">major-seventh</kind>
        </harmony>
      <note>
        <rest/>
        <duration>1</duration>
        <voice>1</voice>
        <type>eighth</type>
        </note>
      <note default-x="31.52" default-y="-50.00">
        <pitch>
          <step>C</step>
          <octave>4</octave>
          </pitch>
        <duration>3</duration>
        <tie type="start"/>
        <voice>1</voice>
        <type>quarter</type>
        <dot/>
        <stem>up</stem>
        <notations>
          <tied type="start"/>
          </notations>
        </note>
      <note default-x="69.61" default-y="-50.00">
        <pitch>
          <step>C</step>
          <octave>4</octave>
          </pitch>
        <duration>2</duration>
        <tie type="stop"/>
        <voice>1</voice>
        <type>quarter</type>
        <stem>up</stem>
        <notations>
          <tied type="stop"/>
          </notations>
        </note>
      <note default-x="100.84" default-y="-35.00">
        <pitch>
          <step>F</step>
          <octave>4</octave>
          </pitch>
        <duration>1</duration>
        <voice>1</voice>
        <type>eighth</type>
        <stem>up</stem>
        <beam number="1">begin</beam>
        </note>
      <note default-x="120.36" default-y="-30.00">
        <pitch>
          <step>G</step>
          <octave>4</octave>
          </pitch>
        <duration>1</duration>
        <voice>1</voice>
        <type>eighth</type>
        <stem>up</stem>
        <beam number="1">end</beam>
        </note>
      </measure>
    <measure number="7" width="171.35">
      <harmony print-frame="no">
        <root>
          <root-step>F</root-step>
          </root>
        <kind text="m7">minor-seventh</kind>
        </harmony>
      <note default-x="15.00" default-y="-25.00">
        <pitch>
          <step>A</step>
          <alter>-1</alter>
          <octave>4</octave>
          </pitch>
        <duration>2</duration>
        <voice>1</voice>
        <type>quarter</type>
        <accidental>flat</accidental>
        <stem>up</stem>
        </note>
      <note default-x="48.96" default-y="-25.00">
        <pitch>
          <step>A</step>
          <alter>-1</alter>
          <octave>4</octave>
          </pitch>
        <duration>1</duration>
        <voice>1</voice>
        <type>eighth</type>
        <stem>up</stem>
        <beam number="1">begin</beam>
        </note>
      <note default-x="70.18" default-y="-25.00">
        <pitch>
          <step>A</step>
          <alter>-1</alter>
          <octave>4</octave>
          </pitch>
        <duration>1</duration>
        <voice>1</voice>
        <type>eighth</type>
        <stem>up</stem>
        <beam number="1">end</beam>
        </note>
      <note default-x="91.40" default-y="-30.00">
        <pitch>
          <step>G</step>
          <octave>4</octave>
          </pitch>
        <duration>2</duration>
        <voice>1</voice>
        <type>quarter</type>
        <stem>up</stem>
        </note>
      <note default-x="125.36" default-y="-20.00">
        <pitch>
          <step>B</step>
          <alter>-1</alter>
          <octave>4</octave>
          </pitch>
        <duration>1</duration>
        <voice>1</voice>
        <type>eighth</type>
        <accidental>flat</accidental>
        <stem>up</stem>
        <beam number="1">begin</beam>
        </note>
      <note default-x="146.59" default-y="-25.00">
        <pitch>
          <step>A</step>
          <alter>-1</alter>
          <octave>4</octave>
          </pitch>
        <duration>1</duration>
        <tie type="start"/>
        <voice>1</voice>
        <type>eighth</type>
        <stem>up</stem>
        <beam number="1">end</beam>
        <notations>
          <tied type="start"/>
          </notations>
        </note>
      </measure>
    <measure number="8" width="212.46">
      <print new-system="yes">
        <system-layout>
          <system-margins>
            <left-margin>-0.00</left-margin>
            <right-margin>0.00</right-margin>
            </system-margins>
          <system-distance>92.50</system-distance>
          </system-layout>
        </print>
      <harmony print-frame="no">
        <root>
          <root-step>B</root-step>
          <root-alter>-1</root-alter>
          </root>
        <kind text="7">dominant</kind>
        </harmony>
      <note default-x="53.15" default-y="-25.00">
        <pitch>
          <step>A</step>
          <alter>-1</alter>
          <octave>4</octave>
          </pitch>
        <duration>6</duration>
        <tie type="stop"/>
        <voice>1</voice>
        <type>half</type>
        <dot/>
        <stem>up</stem>
        <notations>
          <tied type="stop"/>
          </notations>
        </note>
      <note>
        <rest/>
        <duration>1</duration>
        <voice>1</voice>
        <type>eighth</type>
        </note>
      <note default-x="176.21" default-y="-30.00">
        <pitch>
          <step>G</step>
          <octave>4</octave>
          </pitch>
        <duration>1</duration>
        <tie type="start"/>
        <voice>1</voice>
        <type>eighth</type>
        <stem>up</stem>
        <notations>
          <tied type="start"/>
          </notations>
        </note>
      </measure>
    <measure number="9" width="248.53">
      <harmony print-frame="no">
        <root>
          <root-step>E</root-step>
          <root-alter>-1</root-alter>
          </root>
        <kind text="M7">major-seventh</kind>
        </harmony>
      <note default-x="12.00" default-y="-30.00">
        <pitch>
          <step>G</step>
          <octave>4</octave>
          </pitch>
        <duration>2</duration>
        <tie type="stop"/>
        <voice>1</voice>
        <type>quarter</type>
        <stem>up</stem>
        <notations>
          <tied type="stop"/>
          </notations>
        </note>
      <note default-x="64.21" default-y="-35.00">
        <pitch>
          <step>F</step>
          <octave>4</octave>
          </pitch>
        <duration>1</duration>
        <voice>1</voice>
        <type>eighth</type>
        <stem>up</stem>
        <beam number="1">begin</beam>
        </note>
      <note default-x="96.84" default-y="-40.00">
        <pitch>
          <step>E</step>
          <alter>-1</alter>
          <octave>4</octave>
          </pitch>
        <duration>1</duration>
        <voice>1</voice>
        <type>eighth</type>
        <accidental>flat</accidental>
        <stem>up</stem>
        <beam number="1">end</beam>
        </note>
      <note default-x="129.46" default-y="-45.00">
        <pitch>
          <step>D</step>
          <octave>4</octave>
          </pitch>
        <duration>1</duration>
        <voice>1</voice>
        <type>eighth</type>
        <stem>up</stem>
        </note>
      <note default-x="162.09" default-y="-50.00">
        <pitch>
          <step>C</step>
          <octave>4</octave>
          </pitch>
        <duration>2</duration>
        <voice>1</voice>
        <type>quarter</type>
        <stem>up</stem>
        </note>
      <note default-x="214.30" default-y="-30.00">
        <pitch>
          <step>G</step>
          <alter>-1</alter>
          <octave>4</octave>
          </pitch>
        <duration>1</duration>
        <tie type="start"/>
        <voice>1</voice>
        <type>eighth</type>
        <accidental>flat</accidental>
        <stem>up</stem>
        <notations>
          <tied type="start"/>
          </notations>
        </note>
      </measure>
    <measure number="10" width="237.13">
      <harmony print-frame="no">
        <root>
          <root-step>E</root-step>
          <root-alter>-1</root-alter>
          </root>
        <kind text="m7">minor-seventh</kind>
        </harmony>
      <note default-x="12.00" default-y="-30.00">
        <pitch>
          <step>G</step>
          <alter>-1</alter>
          <octave>4</octave>
          </pitch>
        <duration>2</duration>
        <tie type="stop"/>
        <voice>1</voice>
        <type>quarter</type>
        <stem>up</stem>
        <notations>
          <tied type="stop"/>
          </notations>
        </note>
      <note default-x="61.38" default-y="-35.00">
        <pitch>
          <step>F</step>
          <octave>4</octave>
          </pitch>
        <duration>1</duration>
        <voice>1</voice>
        <type>eighth</type>
        <stem>up</stem>
        <beam number="1">begin</beam>
        </note>
      <note default-x="92.25" default-y="-40.00">
        <pitch>
          <step>E</step>
          <alter>-1</alter>
          <octave>4</octave>
          </pitch>
        <duration>1</duration>
        <voice>1</voice>
        <type>eighth</type>
        <accidental>flat</accidental>
        <stem>up</stem>
        <beam number="1">end</beam>
        </note>
      <harmony print-frame="no">
        <root>
          <root-step>A</root-step>
          <root-alter>-1</root-alter>
          </root>
        <kind text="7">dominant</kind>
        </harmony>
      <note default-x="123.11" default-y="-45.00">
        <pitch>
          <step>D</step>
          <octave>4</octave>
          </pitch>
        <duration>1</duration>
        <voice>1</voice>
        <type>eighth</type>
        <stem>up</stem>
        </note>
      <note default-x="153.97" default-y="-50.00">
        <pitch>
          <step>C</step>
          <octave>4</octave>
          </pitch>
        <duration>2</duration>
        <voice>1</voice>
        <type>quarter</type>
        <stem>up</stem>
        </note>
      <note default-x="203.36" default-y="-35.00">
        <pitch>
          <step>F</step>
          <octave>4</octave>
          </pitch>
        <duration>1</duration>
        <tie type="start"/>
        <voice>1</voice>
        <type>eighth</type>
        <stem>up</stem>
        <notations>
          <tied type="start"/>
          </notations>
        </note>
      </measure>
    <measure number="11" width="128.54">
      <harmony print-frame="no">
        <root>
          <root-step>D</root-step>
          <root-alter>-1</root-alter>
          </root>
        <kind text="M7">major-seventh</kind>
        </harmony>
      <note default-x="12.00" default-y="-35.00">
        <pitch>
          <step>F</step>
          <octave>4</octave>
          </pitch>
        <duration>8</duration>
        <tie type="stop"/>
        <voice>1</voice>
        <type>whole</type>
        <notations>
          <tied type="stop"/>
          </notations>
        </note>
      </measure>
    <measure number="12" width="250.51">
      <harmony print-frame="no">
        <root>
          <root-step>C</root-step>
          </root>
        <kind text="halfdim7">half-diminished</kind>
        </harmony>
      <note>
        <rest/>
        <duration>1</duration>
        <voice>1</voice>
        <type>eighth</type>
        </note>
      <note default-x="42.38" default-y="-45.00">
        <pitch>
          <step>D</step>
          <octave>4</octave>
          </pitch>
        <duration>1</duration>
        <voice>1</voice>
        <type>eighth</type>
        <stem>up</stem>
        <beam number="1">begin</beam>
        </note>
      <note default-x="72.77" default-y="-40.00">
        <pitch>
          <step>E</step>
          <alter>-1</alter>
          <octave>4</octave>
          </pitch>
        <duration>1</duration>
        <voice>1</voice>
        <type>eighth</type>
        <accidental>flat</accidental>
        <stem>up</stem>
        <beam number="1">continue</beam>
        </note>
      <note default-x="103.15" default-y="-35.00">
        <pitch>
          <step>F</step>
          <octave>4</octave>
          </pitch>
        <duration>1</duration>
        <voice>1</voice>
        <type>eighth</type>
        <stem>up</stem>
        <beam number="1">end</beam>
        </note>
      <harmony print-frame="no">
        <root>
          <root-step>G</root-step>
          </root>
        <kind text="7b9">dominant</kind>
        <degree>
          <degree-value>9</degree-value>
          <degree-alter>-1</degree-alter>
          <degree-type>add</degree-type>
          </degree>
        </harmony>
      <note default-x="133.53" default-y="-30.00">
        <pitch>
          <step>G</step>
          <octave>4</octave>
          </pitch>
        <duration>1</duration>
        <voice>1</voice>
        <type>eighth</type>
        <stem>up</stem>
        <beam number="1">begin</beam>
        </note>
      <note default-x="163.91" default-y="-25.00">
        <pitch>
          <step>A</step>
          <alter>-1</alter>
          <octave>4</octave>
          </pitch>
        <duration>1</duration>
        <voice>1</voice>
        <type>eighth</type>
        <accidental>flat</accidental>
        <stem>up</stem>
        <beam number="1">end</beam>
        </note>
      <note default-x="194.30" default-y="-20.00">
        <pitch>
          <step>B</step>
          <octave>4</octave>
          </pitch>
        <duration>2</duration>
        <voice>1</voice>
        <type>quarter</type>
        <stem>down</stem>
        </note>
      <barline location="right">
        <bar-style>light-heavy</bar-style>
        </barline>
      </measure>
    </part>
  </score-partwise>
